required_files/__init__.py
required_files/required_files.py
required_files-1.0.2.dist-info/METADATA
required_files-1.0.2.dist-info/WHEEL
required_files-1.0.2.dist-info/namespace_packages.txt
required_files-1.0.2.dist-info/top_level.txt
required_files-1.0.2.dist-info/zip-safe
required_files-1.0.2.dist-info/RECORD
